{
  "clientes": [
    {
      "id": "abc",
      "nome": "Hugo Vinicius",
      "genero": "M",
      "cpf": "789.523.657-89",
      "rg": "896575-85",
      "dataNascimento": "1998-03-02"
    }
  ],
  "contas": [
    {
      "idCliente": "abc",
      "instituicao": "Caixa",
      "agencia": "0006",
      "conta": "000000-00",
      "saldo": 55000,
      "id": "s3-GraV"
    }
  ],
  "cartao-credito": [
    {
      "idCliente": "abc",
      "nome": "Nubank",
      "limite": 66589,
      "valorProximaFatura": 17000,
      "vencimentoFatura": "2023-05-08",
      "diaFechamento": 9,
      "id": 1
    },
    {
      "idCliente": "abc",
      "nome": "Credit Card",
      "limite": 75000,
      "valorProximaFatura": 35000,
      "vencimentoFatura": "2023-05-10",
      "diaFechamento": 10,
      "id": 2
    }
  ]
}